eyja_influxdb/__init__.py
eyja_influxdb/influxdb_hub.py
eyja_influxdb/models/__init__.py
eyja_influxdb/models/time_point.py
eyja_influxdb_hub-0.1.4.dist-info/METADATA
eyja_influxdb_hub-0.1.4.dist-info/WHEEL
eyja_influxdb_hub-0.1.4.dist-info/top_level.txt
eyja_influxdb_hub-0.1.4.dist-info/zip-safe
eyja_influxdb_hub-0.1.4.dist-info/RECORD
